debaterpy/__init__.py
debaterpy/structures.py
debaterpy/utils.py
debaterpy-0.1.1.dist-info/LICENSE
debaterpy-0.1.1.dist-info/METADATA
debaterpy-0.1.1.dist-info/WHEEL
debaterpy-0.1.1.dist-info/top_level.txt
debaterpy-0.1.1.dist-info/RECORD
