Metadata-Version: 2.1
Name: debaterpy
Version: 0.1.1
Summary: A simple library to keep track of your progress and history in competitive debating.
Author-email: Daan Olivier Koning <daanolivierkoning@gmail.com>
Project-URL: Homepage, https://github.com/daankoning/debater.py
Project-URL: Documentation, https://debaterpy.readthedocs.io/en/latest/
Keywords: debating,debate,analysis,statistics
Classifier: Programming Language :: Python :: 3
Classifier: License :: OSI Approved :: MIT License
Classifier: Operating System :: OS Independent
Requires-Python: >=3.9
License-File: LICENSE
